inte_auth/__init__.py
inte_auth/apps.py
inte_auth/codenames_by_group.py
inte_auth/urls.py
inte_auth/codenames/__init__.py
inte_auth/codenames/auditor.py
inte_auth/codenames/clinic.py
inte_auth/codenames/screening.py
inte_auth/codenames/unblinding.py
inte_auth/tests/__init__.py
inte_auth/tests/test_permissions.py
inte_auth/tests/urls.py
inte_auth-0.1.2.dist-info/AUTHORS
inte_auth-0.1.2.dist-info/LICENSE
inte_auth-0.1.2.dist-info/METADATA
inte_auth-0.1.2.dist-info/WHEEL
inte_auth-0.1.2.dist-info/top_level.txt
inte_auth-0.1.2.dist-info/RECORD
